codemetrics_report/__init__.py
codemetrics_report/cli.py
codemetrics_report/codemetrics_template.html
codemetrics_report/filter.py
codemetrics_report/report.py
codemetrics_report/vis.py
codemetrics_report-0.1.1.dist-info/LICENSE.md
codemetrics_report-0.1.1.dist-info/METADATA
codemetrics_report-0.1.1.dist-info/WHEEL
codemetrics_report-0.1.1.dist-info/entry_points.txt
codemetrics_report-0.1.1.dist-info/top_level.txt
codemetrics_report-0.1.1.dist-info/RECORD
