Metadata-Version: 2.1
Name: codemetrics-report
Version: 0.1.1
Summary: Quick reporting of codemetrics minings
Home-page: https://github.com/lpereira95/codemetrics-report
Author: L. F. Pereira
Author-email: luisfgpereira95@gmail.com
License: UNKNOWN
Project-URL: Bug Tracker, https://github.com/lpereira95/codemetrics-report/issues
Keywords: code metrics,code analysis,scm,git
Platform: UNKNOWN
Classifier: Programming Language :: Python :: 3.6
Classifier: Programming Language :: Python :: 3.7
Classifier: Programming Language :: Python :: 3.8
Classifier: Programming Language :: Python :: 3.9
Classifier: Programming Language :: Python :: 3.10
Classifier: License :: OSI Approved :: MIT License
Requires-Python: >=3.6
Requires-Dist: codemetrics
Requires-Dist: altair
Requires-Dist: tqdm
Requires-Dist: numpy
Requires-Dist: pandas
Requires-Dist: click
